jsondatahelper.py
jsondatahelper-0.1.0.dist-info/LICENSE
jsondatahelper-0.1.0.dist-info/METADATA
jsondatahelper-0.1.0.dist-info/WHEEL
jsondatahelper-0.1.0.dist-info/top_level.txt
jsondatahelper-0.1.0.dist-info/RECORD
