Metadata-Version: 2.1
Name: jsondatahelper
Version: 0.1.0
Summary: Collection of utility functions for JSON data manipulation.
Home-page: UNKNOWN
Author: UNKNOWN
Author-email: UNKNOWN
License: UNKNOWN
Platform: UNKNOWN
